pandasai_ibm/__init__.py
pandasai_ibm/ibm_watsonx.py
pandasai_ibm-0.1.5.dist-info/METADATA
pandasai_ibm-0.1.5.dist-info/WHEEL
pandasai_ibm-0.1.5.dist-info/RECORD
